scmcp/__init__.py
scmcp/__main__.py
scmcp/cli.py
scmcp/logging_config.py
scmcp/server.py
scmcp/util.py
scmcp/schema/__init__.py
scmcp/schema/base.py
scmcp/schema/ccc.py
scmcp/schema/io.py
scmcp/schema/pl.py
scmcp/schema/pp.py
scmcp/schema/tl.py
scmcp/schema/util.py
scmcp/tool/__init__.py
scmcp/tool/ccc.py
scmcp/tool/io.py
scmcp/tool/pl.py
scmcp/tool/pp.py
scmcp/tool/tl.py
scmcp/tool/util.py
iflow_mcp_scmcp-0.1.3.dist-info/METADATA
iflow_mcp_scmcp-0.1.3.dist-info/WHEEL
iflow_mcp_scmcp-0.1.3.dist-info/entry_points.txt
iflow_mcp_scmcp-0.1.3.dist-info/licenses/LICENSE
iflow_mcp_scmcp-0.1.3.dist-info/RECORD
