Metadata-Version: 2.4
Name: iflow-mcp_scmcp
Version: 0.1.3
Summary: An MCP server for scRNA-Seq analysis with natural language!
Author-email: shuang <hsh-me@outlook.com>
License: BSD 3-Clause License
License-File: LICENSE
Requires-Python: >=3.10
Requires-Dist: cellrank>=2.0.7
Requires-Dist: igraph
Requires-Dist: liana; sys_platform != 'win32'
Requires-Dist: mcp
Requires-Dist: pydantic
Requires-Dist: scanpy
